{"namespace":"CortanaTechDesignSystem_bb1f31","components":[{"name":"BlogCard","sourcePath":"components/cards/BlogCard.jsx"},{"name":"Card","sourcePath":"components/cards/Card.jsx"},{"name":"TeamCard","sourcePath":"components/cards/TeamCard.jsx"},{"name":"Badge","sourcePath":"components/core/Badge.jsx"},{"name":"Button","sourcePath":"components/core/Button.jsx"},{"name":"SectionHeader","sourcePath":"components/core/SectionHeader.jsx"},{"name":"ServiceItem","sourcePath":"components/core/ServiceItem.jsx"},{"name":"Input","sourcePath":"components/forms/Input.jsx"},{"name":"Navbar","sourcePath":"components/navigation/Navbar.jsx"}],"startingPoints":[{"name":"Button","path":"components/core/Button.jsx","previewPath":"components/core/buttons.card.html","kind":"component","section":"Components","subtitle":"Primary, outline, ghost — all sizes","viewport":"700x120"},{"name":"website","path":"ui_kits/website/index.html","previewPath":"ui_kits/website/index.html","kind":"screen","section":"Website","subtitle":"CortanaTech homepage — hero, services, blog, CTA, footer","viewport":"1280x800"}],"cards":[{"path":"guidelines/brand-logo.card.html","group":"Brand","viewport":"700x280","subtitle":"Path-based outline SVGs — font-independent, render everywhere","name":"Logo Variants"},{"path":"guidelines/brand-photography.card.html","group":"Brand","viewport":"700x280","subtitle":"Brand photo library — team shots, working scenes, individual portraits","name":"Photography"},{"path":"guidelines/brand-sections.card.html","group":"Brand","viewport":"700x180","subtitle":"The three page-section background treatments used throughout the site","name":"Section Backgrounds"},{"path":"guidelines/brand-voice.card.html","group":"Brand","viewport":"700x260","subtitle":"Tone, copy style, and writing principles","name":"Brand Voice"},{"path":"guidelines/colors-brand.card.html","group":"Colors","viewport":"700x180","subtitle":"Primary blue and navy — the two core brand hues","name":"Brand Blues"},{"path":"guidelines/colors-gradient.card.html","group":"Colors","viewport":"700x160","subtitle":"The signature blue-to-navy gradient used on hero overlays, CTA banners, and logo backgrounds","name":"Brand Gradient"},{"path":"guidelines/colors-neutral.card.html","group":"Colors","viewport":"700x180","subtitle":"Warm grays used for text, borders, and surfaces","name":"Neutral Scale"},{"path":"guidelines/colors-semantic.card.html","group":"Colors","viewport":"700x140","subtitle":"Status and feedback colors — success, warning, error, info","name":"Semantic Colors"},{"path":"components/cards/cards.card.html","group":"Components","viewport":"700x220","subtitle":"Blog, Team, and generic Card components","name":"Cards"},{"path":"components/core/buttons.card.html","group":"Components","viewport":"700x200","subtitle":"Primary, navy, outline, ghost — all sizes and states","name":"Buttons"},{"path":"components/core/core.card.html","group":"Components","viewport":"700x180","subtitle":"SectionHeader, Badge, ServiceItem — building blocks for page sections","name":"Core Components"},{"path":"components/forms/forms.card.html","group":"Components","viewport":"700x220","subtitle":"Input, labels, states — for sign-up and contact forms","name":"Forms"},{"path":"components/navigation/navigation.card.html","group":"Components","viewport":"700x80","subtitle":"Sticky top navbar with logo, links, and CTA","name":"Navigation"},{"path":"guidelines/shadows-radius.card.html","group":"Spacing","viewport":"700x220","subtitle":"Elevation shadows and border-radius tokens","name":"Shadows & Radii"},{"path":"guidelines/spacing-scale.card.html","group":"Spacing","viewport":"700x140","subtitle":"4px base unit — --space-1 through --space-32","name":"Spacing Scale"},{"path":"guidelines/type-body.card.html","group":"Type","viewport":"700x200","subtitle":"DM Sans — readable body copy, labels, and interface text","name":"Body & UI Text"},{"path":"guidelines/type-display.card.html","group":"Type","viewport":"700x220","subtitle":"Urbanist — the brand's display typeface for all headlines","name":"Display & Headings"},{"path":"guidelines/type-scale.card.html","group":"Type","viewport":"700x160","subtitle":"Token reference — size, weight, and role in one view","name":"Type Scale"},{"path":"ui_kits/website/index.html","group":"Website","viewport":"1280x800","subtitle":"Full homepage — nav, hero, services, testimonial, blog, CTA, footer","name":"CortanaTech Website"}],"templates":[],"globalCssPaths":["tokens/fonts.css","tokens/colors.css","tokens/typography.css","tokens/spacing.css","tokens/shadows.css","styles.css"],"tokens":[{"name":"--color-blue-50","value":"#EBF4FB","kind":"color","definedIn":"tokens/colors.css"},{"name":"--color-blue-100","value":"#C5DFF2","kind":"color","definedIn":"tokens/colors.css"},{"name":"--color-blue-200","value":"#9ECBEA","kind":"color","definedIn":"tokens/colors.css"},{"name":"--color-blue-300","value":"#5FA8D8","kind":"color","definedIn":"tokens/colors.css"},{"name":"--color-blue-400","value":"#2E85C2","kind":"color","definedIn":"tokens/colors.css"},{"name":"--color-blue-500","value":"#1C75BC","kind":"color","definedIn":"tokens/colors.css"},{"name":"--color-blue-600","value":"#1863A3","kind":"color","definedIn":"tokens/colors.css"},{"name":"--color-blue-700","value":"#14518A","kind":"color","definedIn":"tokens/colors.css"},{"name":"--color-blue-800","value":"#2B3990","kind":"color","definedIn":"tokens/colors.css"},{"name":"--color-blue-900","value":"#1E2A70","kind":"color","definedIn":"tokens/colors.css"},{"name":"--color-neutral-0","value":"#FFFFFF","kind":"color","definedIn":"tokens/colors.css"},{"name":"--color-neutral-50","value":"#F1EDED","kind":"color","definedIn":"tokens/colors.css"},{"name":"--color-neutral-100","value":"#E8E6E6","kind":"color","definedIn":"tokens/colors.css"},{"name":"--color-neutral-200","value":"#D1D0CE","kind":"color","definedIn":"tokens/colors.css"},{"name":"--color-neutral-300","value":"#B5B3B0","kind":"color","definedIn":"tokens/colors.css"},{"name":"--color-neutral-400","value":"#8C909A","kind":"color","definedIn":"tokens/colors.css"},{"name":"--color-neutral-500","value":"#6B6F7A","kind":"color","definedIn":"tokens/colors.css"},{"name":"--color-neutral-600","value":"#454C59","kind":"color","definedIn":"tokens/colors.css"},{"name":"--color-neutral-700","value":"#2D3142","kind":"color","definedIn":"tokens/colors.css"},{"name":"--color-neutral-800","value":"#1E1F1E","kind":"color","definedIn":"tokens/colors.css"},{"name":"--color-neutral-900","value":"#0F1011","kind":"color","definedIn":"tokens/colors.css"},{"name":"--color-primary","value":"var(--color-blue-500)","kind":"color","definedIn":"tokens/colors.css"},{"name":"--color-primary-dark","value":"var(--color-blue-800)","kind":"color","definedIn":"tokens/colors.css"},{"name":"--color-primary-light","value":"var(--color-blue-400)","kind":"color","definedIn":"tokens/colors.css"},{"name":"--color-primary-subtle","value":"var(--color-blue-50)","kind":"color","definedIn":"tokens/colors.css"},{"name":"--color-text-primary","value":"var(--color-neutral-800)","kind":"font","definedIn":"tokens/colors.css"},{"name":"--color-text-secondary","value":"var(--color-neutral-600)","kind":"font","definedIn":"tokens/colors.css"},{"name":"--color-text-muted","value":"var(--color-neutral-400)","kind":"font","definedIn":"tokens/colors.css"},{"name":"--color-text-inverse","value":"var(--color-neutral-0)","kind":"font","definedIn":"tokens/colors.css"},{"name":"--color-text-accent","value":"var(--color-blue-500)","kind":"font","definedIn":"tokens/colors.css"},{"name":"--color-surface-default","value":"var(--color-neutral-0)","kind":"color","definedIn":"tokens/colors.css"},{"name":"--color-surface-subtle","value":"var(--color-neutral-50)","kind":"color","definedIn":"tokens/colors.css"},{"name":"--color-surface-navy","value":"var(--color-blue-800)","kind":"color","definedIn":"tokens/colors.css"},{"name":"--color-surface-blue","value":"var(--color-blue-500)","kind":"color","definedIn":"tokens/colors.css"},{"name":"--color-border-default","value":"var(--color-neutral-200)","kind":"color","definedIn":"tokens/colors.css"},{"name":"--color-border-subtle","value":"var(--color-neutral-100)","kind":"color","definedIn":"tokens/colors.css"},{"name":"--color-border-focus","value":"var(--color-blue-500)","kind":"color","definedIn":"tokens/colors.css"},{"name":"--color-blue-sky","value":"#29ABE2","kind":"color","definedIn":"tokens/colors.css"},{"name":"--gradient-brand","value":"linear-gradient(135deg, #29ABE2 0%, #2E3192 100%)","kind":"color","definedIn":"tokens/colors.css","annotation":"color"},{"name":"--gradient-brand-overlay","value":"linear-gradient(135deg, rgba(41,171,226,0.82) 0%, rgba(46,49,146,0.82) 100%)","kind":"color","definedIn":"tokens/colors.css","annotation":"color"},{"name":"--gradient-brand-overlay-dark","value":"linear-gradient(135deg, rgba(41,171,226,0.92) 0%, rgba(46,49,146,0.92) 100%)","kind":"color","definedIn":"tokens/colors.css","annotation":"color"},{"name":"--color-success","value":"#1A7F4B","kind":"color","definedIn":"tokens/colors.css"},{"name":"--color-warning","value":"#C8821A","kind":"color","definedIn":"tokens/colors.css"},{"name":"--color-error","value":"#C0392B","kind":"color","definedIn":"tokens/colors.css"},{"name":"--color-info","value":"var(--color-blue-500)","kind":"color","definedIn":"tokens/colors.css"},{"name":"--font-display","value":"'Urbanist', sans-serif","kind":"font","definedIn":"tokens/typography.css"},{"name":"--font-body","value":"'DM Sans', sans-serif","kind":"font","definedIn":"tokens/typography.css"},{"name":"--font-mono","value":"'DM Mono', monospace","kind":"font","definedIn":"tokens/typography.css"},{"name":"--text-xs","value":"0.75rem","kind":"font","definedIn":"tokens/typography.css"},{"name":"--text-sm","value":"0.875rem","kind":"font","definedIn":"tokens/typography.css"},{"name":"--text-base","value":"1rem","kind":"font","definedIn":"tokens/typography.css"},{"name":"--text-md","value":"1.125rem","kind":"font","definedIn":"tokens/typography.css"},{"name":"--text-lg","value":"1.25rem","kind":"font","definedIn":"tokens/typography.css"},{"name":"--text-xl","value":"1.5rem","kind":"font","definedIn":"tokens/typography.css"},{"name":"--text-2xl","value":"2rem","kind":"font","definedIn":"tokens/typography.css"},{"name":"--text-3xl","value":"2.5rem","kind":"font","definedIn":"tokens/typography.css"},{"name":"--text-4xl","value":"3rem","kind":"font","definedIn":"tokens/typography.css"},{"name":"--text-5xl","value":"3.75rem","kind":"font","definedIn":"tokens/typography.css"},{"name":"--text-6xl","value":"4.5rem","kind":"font","definedIn":"tokens/typography.css"},{"name":"--font-regular","value":"400","kind":"font","definedIn":"tokens/typography.css"},{"name":"--font-medium","value":"500","kind":"font","definedIn":"tokens/typography.css"},{"name":"--font-semibold","value":"600","kind":"font","definedIn":"tokens/typography.css"},{"name":"--font-bold","value":"700","kind":"font","definedIn":"tokens/typography.css"},{"name":"--font-black","value":"900","kind":"font","definedIn":"tokens/typography.css"},{"name":"--leading-none","value":"1","kind":"font","definedIn":"tokens/typography.css"},{"name":"--leading-tight","value":"1.2","kind":"font","definedIn":"tokens/typography.css"},{"name":"--leading-snug","value":"1.35","kind":"font","definedIn":"tokens/typography.css"},{"name":"--leading-normal","value":"1.5","kind":"font","definedIn":"tokens/typography.css"},{"name":"--leading-relaxed","value":"1.625","kind":"font","definedIn":"tokens/typography.css"},{"name":"--leading-loose","value":"1.75","kind":"font","definedIn":"tokens/typography.css"},{"name":"--tracking-tight","value":"-0.025em","kind":"font","definedIn":"tokens/typography.css"},{"name":"--tracking-snug","value":"-0.01em","kind":"font","definedIn":"tokens/typography.css"},{"name":"--tracking-normal","value":"0","kind":"font","definedIn":"tokens/typography.css"},{"name":"--tracking-wide","value":"0.05em","kind":"font","definedIn":"tokens/typography.css"},{"name":"--tracking-wider","value":"0.08em","kind":"font","definedIn":"tokens/typography.css"},{"name":"--tracking-widest","value":"0.12em","kind":"font","definedIn":"tokens/typography.css"},{"name":"--type-display-font","value":"var(--font-display)","kind":"font","definedIn":"tokens/typography.css"},{"name":"--type-display-weight","value":"var(--font-black)","kind":"font","definedIn":"tokens/typography.css"},{"name":"--type-display-leading","value":"var(--leading-tight)","kind":"font","definedIn":"tokens/typography.css"},{"name":"--type-display-tracking","value":"var(--tracking-tight)","kind":"font","definedIn":"tokens/typography.css"},{"name":"--type-heading-font","value":"var(--font-display)","kind":"font","definedIn":"tokens/typography.css"},{"name":"--type-heading-weight","value":"var(--font-bold)","kind":"font","definedIn":"tokens/typography.css"},{"name":"--type-heading-leading","value":"var(--leading-snug)","kind":"font","definedIn":"tokens/typography.css"},{"name":"--type-eyebrow-font","value":"var(--font-body)","kind":"font","definedIn":"tokens/typography.css"},{"name":"--type-eyebrow-weight","value":"var(--font-semibold)","kind":"font","definedIn":"tokens/typography.css"},{"name":"--type-eyebrow-tracking","value":"var(--tracking-wide)","kind":"font","definedIn":"tokens/typography.css"},{"name":"--type-eyebrow-size","value":"var(--text-sm)","kind":"font","definedIn":"tokens/typography.css"},{"name":"--type-body-font","value":"var(--font-body)","kind":"font","definedIn":"tokens/typography.css"},{"name":"--type-body-weight","value":"var(--font-regular)","kind":"font","definedIn":"tokens/typography.css"},{"name":"--type-body-leading","value":"var(--leading-relaxed)","kind":"font","definedIn":"tokens/typography.css"},{"name":"--type-label-font","value":"var(--font-body)","kind":"font","definedIn":"tokens/typography.css"},{"name":"--type-label-weight","value":"var(--font-medium)","kind":"font","definedIn":"tokens/typography.css"},{"name":"--space-0","value":"0","kind":"spacing","definedIn":"tokens/spacing.css"},{"name":"--space-px","value":"1px","kind":"spacing","definedIn":"tokens/spacing.css"},{"name":"--space-1","value":"4px","kind":"spacing","definedIn":"tokens/spacing.css"},{"name":"--space-2","value":"8px","kind":"spacing","definedIn":"tokens/spacing.css"},{"name":"--space-3","value":"12px","kind":"spacing","definedIn":"tokens/spacing.css"},{"name":"--space-4","value":"16px","kind":"spacing","definedIn":"tokens/spacing.css"},{"name":"--space-5","value":"20px","kind":"spacing","definedIn":"tokens/spacing.css"},{"name":"--space-6","value":"24px","kind":"spacing","definedIn":"tokens/spacing.css"},{"name":"--space-7","value":"28px","kind":"spacing","definedIn":"tokens/spacing.css"},{"name":"--space-8","value":"32px","kind":"spacing","definedIn":"tokens/spacing.css"},{"name":"--space-9","value":"36px","kind":"spacing","definedIn":"tokens/spacing.css"},{"name":"--space-10","value":"40px","kind":"spacing","definedIn":"tokens/spacing.css"},{"name":"--space-12","value":"48px","kind":"spacing","definedIn":"tokens/spacing.css"},{"name":"--space-14","value":"56px","kind":"spacing","definedIn":"tokens/spacing.css"},{"name":"--space-16","value":"64px","kind":"spacing","definedIn":"tokens/spacing.css"},{"name":"--space-20","value":"80px","kind":"spacing","definedIn":"tokens/spacing.css"},{"name":"--space-24","value":"96px","kind":"spacing","definedIn":"tokens/spacing.css"},{"name":"--space-28","value":"112px","kind":"spacing","definedIn":"tokens/spacing.css"},{"name":"--space-32","value":"128px","kind":"spacing","definedIn":"tokens/spacing.css"},{"name":"--radius-none","value":"0","kind":"radius","definedIn":"tokens/spacing.css"},{"name":"--radius-xs","value":"2px","kind":"radius","definedIn":"tokens/spacing.css"},{"name":"--radius-sm","value":"4px","kind":"radius","definedIn":"tokens/spacing.css"},{"name":"--radius-md","value":"8px","kind":"radius","definedIn":"tokens/spacing.css"},{"name":"--radius-lg","value":"12px","kind":"radius","definedIn":"tokens/spacing.css"},{"name":"--radius-xl","value":"16px","kind":"radius","definedIn":"tokens/spacing.css"},{"name":"--radius-2xl","value":"24px","kind":"radius","definedIn":"tokens/spacing.css"},{"name":"--radius-3xl","value":"32px","kind":"radius","definedIn":"tokens/spacing.css"},{"name":"--radius-full","value":"9999px","kind":"radius","definedIn":"tokens/spacing.css"},{"name":"--container-narrow","value":"720px","kind":"spacing","definedIn":"tokens/spacing.css"},{"name":"--container-default","value":"1200px","kind":"spacing","definedIn":"tokens/spacing.css"},{"name":"--container-wide","value":"1400px","kind":"spacing","definedIn":"tokens/spacing.css"},{"name":"--container-full","value":"100%","kind":"spacing","definedIn":"tokens/spacing.css"},{"name":"--header-height","value":"72px","kind":"spacing","definedIn":"tokens/spacing.css"},{"name":"--sidebar-width","value":"260px","kind":"spacing","definedIn":"tokens/spacing.css"},{"name":"--icon-sm","value":"16px","kind":"spacing","definedIn":"tokens/spacing.css"},{"name":"--icon-md","value":"24px","kind":"spacing","definedIn":"tokens/spacing.css"},{"name":"--icon-lg","value":"32px","kind":"spacing","definedIn":"tokens/spacing.css"},{"name":"--icon-xl","value":"48px","kind":"spacing","definedIn":"tokens/spacing.css"},{"name":"--section-padding-y","value":"var(--space-20)","kind":"spacing","definedIn":"tokens/spacing.css"},{"name":"--section-padding-x","value":"var(--space-8)","kind":"spacing","definedIn":"tokens/spacing.css"},{"name":"--shadow-none","value":"none","kind":"shadow","definedIn":"tokens/shadows.css"},{"name":"--shadow-xs","value":"0 1px 2px rgba(0, 0, 0, 0.05)","kind":"shadow","definedIn":"tokens/shadows.css"},{"name":"--shadow-sm","value":"0 1px 3px rgba(0, 0, 0, 0.1), 0 1px 2px rgba(0, 0, 0, 0.06)","kind":"shadow","definedIn":"tokens/shadows.css"},{"name":"--shadow-md","value":"0 4px 6px rgba(0, 0, 0, 0.07), 0 2px 4px rgba(0, 0, 0, 0.05)","kind":"shadow","definedIn":"tokens/shadows.css"},{"name":"--shadow-lg","value":"0 10px 15px rgba(0, 0, 0, 0.08), 0 4px 6px rgba(0, 0, 0, 0.04)","kind":"shadow","definedIn":"tokens/shadows.css"},{"name":"--shadow-xl","value":"0 20px 25px rgba(0, 0, 0, 0.08), 0 10px 10px rgba(0, 0, 0, 0.04)","kind":"shadow","definedIn":"tokens/shadows.css"},{"name":"--shadow-2xl","value":"0 25px 50px rgba(0, 0, 0, 0.12)","kind":"shadow","definedIn":"tokens/shadows.css"},{"name":"--shadow-inner","value":"inset 0 2px 4px rgba(0, 0, 0, 0.06)","kind":"shadow","definedIn":"tokens/shadows.css"},{"name":"--shadow-card","value":"0 2px 8px rgba(0, 0, 0, 0.06), 0 1px 3px rgba(0, 0, 0, 0.04)","kind":"shadow","definedIn":"tokens/shadows.css"},{"name":"--shadow-card-hover","value":"0 6px 20px rgba(28, 117, 188, 0.12), 0 2px 8px rgba(0, 0, 0, 0.06)","kind":"shadow","definedIn":"tokens/shadows.css"},{"name":"--shadow-nav","value":"0 1px 4px rgba(0, 0, 0, 0.08)","kind":"shadow","definedIn":"tokens/shadows.css"},{"name":"--shadow-modal","value":"0 25px 60px rgba(0, 0, 0, 0.15), 0 8px 20px rgba(0, 0, 0, 0.08)","kind":"shadow","definedIn":"tokens/shadows.css"},{"name":"--shadow-button","value":"0 2px 6px rgba(28, 117, 188, 0.3)","kind":"shadow","definedIn":"tokens/shadows.css"},{"name":"--shadow-focus","value":"0 0 0 3px rgba(28, 117, 188, 0.25)","kind":"shadow","definedIn":"tokens/shadows.css"},{"name":"--overlay-default","value":"rgba(15, 16, 17, 0.5)","kind":"color","definedIn":"tokens/shadows.css"},{"name":"--overlay-heavy","value":"rgba(15, 16, 17, 0.8)","kind":"color","definedIn":"tokens/shadows.css"}],"themes":[],"fonts":[],"brandFonts":[{"family":"Urbanist","status":"ok","tokens":["--font-display"],"path":"tokens/typography.css"},{"family":"DM Sans","status":"ok","tokens":["--font-body"],"path":"tokens/typography.css"},{"family":"DM Mono","status":"ok","tokens":["--font-mono"],"path":"tokens/typography.css"}],"source":"spa"}